Wikipedia2PDF/__init__.py
Wikipedia2PDF-1.0.dist-info/METADATA
Wikipedia2PDF-1.0.dist-info/WHEEL
Wikipedia2PDF-1.0.dist-info/top_level.txt
Wikipedia2PDF-1.0.dist-info/RECORD
