Metadata-Version: 2.1
Name: Wikipedia2PDF
Version: 1.0
Summary: Convert any Wikipedia article into PDF.
Home-page: https://github.com/cj-praveen/Wikipedia2PDF/
License: MIT
Requires-Python: >=3.6
